CHANGES.txt
CONTRIBUTORS.txt
MANIFEST.in
README.txt
setup.cfg
setup.py
collective/__init__.py
collective.taghelper.egg-info/PKG-INFO
collective.taghelper.egg-info/SOURCES.txt
collective.taghelper.egg-info/dependency_links.txt
collective.taghelper.egg-info/entry_points.txt
collective.taghelper.egg-info/namespace_packages.txt
collective.taghelper.egg-info/not-zip-safe
collective.taghelper.egg-info/paster_plugins.txt
collective.taghelper.egg-info/requires.txt
collective.taghelper.egg-info/top_level.txt
collective/taghelper/AlchemyAPI.py
collective/taghelper/README.txt
collective/taghelper/__init__.py
collective/taghelper/amplify.py
collective/taghelper/calais.py
collective/taghelper/config.py
collective/taghelper/configure.zcml
collective/taghelper/evri.py
collective/taghelper/setuphandlers.py
collective/taghelper/silcc.py
collective/taghelper/tagthenet.py
collective/taghelper/utilities.py
collective/taghelper/vocabularies.py
collective/taghelper/zemanta.py
collective/taghelper/browser/__init__.py
collective/taghelper/browser/configure.zcml
collective/taghelper/browser/etsnippetview.pt
collective/taghelper/browser/extractedtermsview.pt
collective/taghelper/browser/extractedtermsview.py
collective/taghelper/browser/filehtmlpreviewview.pt
collective/taghelper/browser/filehtmlpreviewview.py
collective/taghelper/browser/taghelpersettings.py
collective/taghelper/interfaces/__init__.py
collective/taghelper/interfaces/taghelpersettings.py
collective/taghelper/profiles/default/actions.xml
collective/taghelper/profiles/default/controlpanel.xml
collective/taghelper/profiles/default/factorytool.xml
collective/taghelper/profiles/default/metadata.xml
collective/taghelper/profiles/default/portlets.xml
collective/taghelper/profiles/default/registry.xml
collective/taghelper/profiles/default/types.xml
collective/taghelper/tests/__init__.py
collective/taghelper/tests/base.py
collective/taghelper/tests/test_doctest.py
docs/LICENSE.GPL
docs/LICENSE.txt