Metadata-Version: 1.0
Name: collective.taghelper
Version: 0.3.1
Summary: The act of tagging content is tedious and humans will often fail to do it. Taghelper examines the content and extracts the keywords that are most relevant.
Home-page: http://plone.org/products/collective.taghelper/
Author: Christian Ledermann
Author-email: christian.ledermann@gmail.com
License: GPL
Platform: UNKNOWN
Classifier: Framework :: Plone
Classifier: Framework :: Plone :: 4.0
Classifier: Framework :: Plone :: 4.1
Classifier: License :: OSI Approved :: GNU General Public License (GPL)
Classifier: Development Status :: 5 - Production/Stable
